{
  "mode": "multimodal",
  "best_val_acc": 94.181,
  "final_train_acc": 98.925,
  "final_val_acc": 94.119,
  "metrics": {
    "macro_avg": {
      "precision": 81.59,
      "recall": 81.49,
      "f1_score": 81.31
    },
    "micro_avg": {
      "precision": 94.12,
      "recall": 94.12,
      "f1_score": 94.12
    },
    "weighted_avg": {
      "precision": 94.15,
      "recall": 94.12,
      "f1_score": 94.07
    },
    "per_class": {
      "class_0": {
        "precision": 83.28,
        "recall": 88.93,
        "f1_score": 86.01
      },
      "class_1": {
        "precision": 44.94,
        "recall": 55.56,
        "f1_score": 49.69
      },
      "class_2": {
        "precision": 75.57,
        "recall": 54.4,
        "f1_score": 63.26
      },
      "class_3": {
        "precision": 96.7,
        "recall": 96.4,
        "f1_score": 96.55
      },
      "class_4": {
        "precision": 75.74,
        "recall": 78.63,
        "f1_score": 77.15
      },
      "class_5": {
        "precision": 87.77,
        "recall": 84.45,
        "f1_score": 86.08
      },
      "class_6": {
        "precision": 58.77,
        "recall": 57.76,
        "f1_score": 58.26
      },
      "class_7": {
        "precision": 99.64,
        "recall": 99.44,
        "f1_score": 99.54
      },
      "class_8": {
        "precision": 88.44,
        "recall": 90.99,
        "f1_score": 89.7
      },
      "class_9": {
        "precision": 87.5,
        "recall": 90.06,
        "f1_score": 88.76
      },
      "class_10": {
        "precision": 99.1,
        "recall": 99.75,
        "f1_score": 99.43
      }
    }
  },
  "history": {
    "train_loss": [
      0.39817722917409243,
      0.23703114834788433,
      0.18242253844196657,
      0.14191957536066543,
      0.1147017665283843,
      0.09342387267051307,
      0.07297450629808208,
      0.0643538743757022,
      0.05514909648740574,
      0.048077219016092326,
      0.04115807161711343,
      0.03798120874907182,
      0.0370860294061619,
      0.03202571174357831,
      0.029838033570890824
    ],
    "train_acc": [
      87.515,
      92.097,
      93.765,
      95.084,
      96.039,
      96.807,
      97.544,
      97.796,
      98.002,
      98.394,
      98.599,
      98.661,
      98.76599999999999,
      98.875,
      98.925
    ],
    "val_loss": [
      0.2784139473650867,
      0.23592992843755528,
      0.22341664952287946,
      0.20334945659412368,
      0.20109899458178288,
      0.20229582665597654,
      0.23881961023710863,
      0.22906412846751611,
      0.22145121946710244,
      0.21835941996439923,
      0.2379887276948644,
      0.2556612844144373,
      0.2526867438160517,
      0.27381888547804434,
      0.25108236958962443
    ],
    "val_acc": [
      91.449,
      92.66,
      92.815,
      93.669,
      93.886,
      93.917,
      93.855,
      93.529,
      93.87,
      94.181,
      94.08800000000001,
      93.715,
      94.16499999999999,
      93.948,
      94.119
    ]
  },
  "args": {
    "gpu_id": "cuda:0",
    "lr": 0.0003,
    "batch_size": 8,
    "num_epochs": 15,
    "seed": 1111,
    "mode": "multimodal",
    "adapter_dim": 8,
    "num_latent": 4,
    "num_classes": 11,
    "csv_file": "/home/research/Agri-MBT/data/aligned_output/aligned_data.csv",
    "data_dir": "/home/research/Agri-MBT",
    "test_size": 0.2,
    "output_dir": "/home/research/Agri-MBT/experiments",
    "device": "cuda:0"
  }
}